issubclass.py
issubclass-0.1.1.dist-info/LICENSE
issubclass-0.1.1.dist-info/WHEEL
issubclass-0.1.1.dist-info/METADATA
issubclass-0.1.1.dist-info/RECORD
